KlucherModelSDas/__init__.py
KlucherModelSDas-1.0.1.dist-info/LICENSE.txt
KlucherModelSDas-1.0.1.dist-info/METADATA
KlucherModelSDas-1.0.1.dist-info/WHEEL
KlucherModelSDas-1.0.1.dist-info/top_level.txt
KlucherModelSDas-1.0.1.dist-info/RECORD
