Metadata-Version: 2.1
Name: KlucherModelSDas
Version: 1.0.1
Summary: Simulator for Klucher Model
Home-page: https://github.com/SubhayanDas08/KlucherModelSimuator_Package
Author: Subhayan Das
Author-email: nips.subhayan@gmail.com
License: MIT
Keywords: klucher,solar,simulator
Platform: UNKNOWN
Classifier: Development Status :: 5 - Production/Stable
Classifier: Intended Audience :: Education
Classifier: Operating System :: Microsoft :: Windows :: Windows 10
Classifier: License :: OSI Approved :: MIT License
Classifier: Programming Language :: Python :: 3
Requires-Dist: XlsxWriter (~=1.3.7)
Provides-Extra: dev
Requires-Dist: pytest (>=3.7) ; extra == 'dev'
